src/toobigdatadoc/__init__.py
src/toobigdatadoc/too.py
desertislandutils-0.1.0.dist-info/entry_points.txt
desertislandutils-0.1.0.dist-info/WHEEL
desertislandutils-0.1.0.dist-info/METADATA
desertislandutils-0.1.0.dist-info/RECORD
