Metadata-Version: 2.1
Name: desertislandutils
Version: 0.1.0
Summary: A collection of personal convenience utilities
License: MIT
Author: mahiki
Author-email: mahiki@users.noreply.github.com
Requires-Python: >=3.9,<4.0
Classifier: License :: OSI Approved :: MIT License
Classifier: Programming Language :: Python :: 3
Classifier: Programming Language :: Python :: 3.10
Classifier: Programming Language :: Python :: 3.9
Requires-Dist: GitPython (>=3.1.27,<4.0.0)
Requires-Dist: argparse (>=1.4.0,<2.0.0)
